README.md
setup.py
fizzbuzz_env/__init__.py
fizzbuzz_env/__main__.py
fizzbuzz_env.egg-info/PKG-INFO
fizzbuzz_env.egg-info/SOURCES.txt
fizzbuzz_env.egg-info/dependency_links.txt
fizzbuzz_env.egg-info/top_level.txt