Metadata-Version: 2.1
Name: fizzbuzz-env
Version: 0.1.1
Summary: have a script play a game of fizzbuzz
Home-page: https://github.com/TRedRaven/fizzbuzz
Author: Red
License: UNKNOWN
Platform: UNKNOWN
Classifier: Programming Language :: Python :: 3
Classifier: License :: OSI Approved :: MIT License
Classifier: Operating System :: OS Independent
Requires-Python: >=3.6
